ALbedo/__init__.py
ALbedo/classes.py
ALbedo/classification.py
ALbedo/pretrainedmodel.py
ALbedo/sampling.py
ALbedo-0.1.dist-info/LICENSE
ALbedo-0.1.dist-info/METADATA
ALbedo-0.1.dist-info/WHEEL
ALbedo-0.1.dist-info/top_level.txt
ALbedo-0.1.dist-info/RECORD
