Metadata-Version: 2.1
Name: ALbedo
Version: 0.1
Summary: A package for pre-trained image classification and context-decider for question-answering chatbots.
Author: Sohini Bhattacharya
Author-email: mail.sohinibhattacharya@gmail.com
Keywords: python,image-classification,active-learning-sampling,question-answering,pre-trained models,tiny-image-net,speech-recognition,cifar10
Classifier: Development Status :: 5 - Production/Stable
Classifier: Intended Audience :: Education
Classifier: License :: OSI Approved :: MIT License
Classifier: Programming Language :: Python :: 3
License-File: LICENSE
Requires-Dist: wget
Requires-Dist: pytesseract
Requires-Dist: bayesian-optimization
Requires-Dist: PyPDF2
Requires-Dist: googletrans ==3.1.0a0
Requires-Dist: speechrecognition
Requires-Dist: pyttsx3
Requires-Dist: pydub
Requires-Dist: torch
Requires-Dist: transformers
Requires-Dist: gdown
Requires-Dist: numpy
Requires-Dist: pandas
Requires-Dist: tensorflow ==2.14
Requires-Dist: datetime
Requires-Dist: keras ==2.14
Requires-Dist: tensorflow-datasets ==4.9.2
Requires-Dist: scipy ==1.10.1
Requires-Dist: tqdm ==4.65.0
